cs_rankings/__init__.py
cs_rankings/client.py
cs_rankings-0.2.2.dist-info/METADATA
cs_rankings-0.2.2.dist-info/WHEEL
cs_rankings-0.2.2.dist-info/licenses/LICENCE
cs_rankings-0.2.2.dist-info/RECORD
