Metadata-Version: 2.4
Name: cs-rankings
Version: 0.2.2
Summary: Pull competitive Counterstrike rankings from HLTV.org, ESL and Valve.
Project-URL: Homepage, https://github.com/debruijn/cs_rankings
Project-URL: Bug Tracker, https://github.com/debruijn/cs_rankings/issues
Author-email: Bert de Bruijn <lpdebruijn@gmail.com>
License: MIT License
License-File: LICENCE
Classifier: License :: OSI Approved :: MIT License
Classifier: Operating System :: OS Independent
Classifier: Programming Language :: Python :: 3
Requires-Python: >=3.10
Requires-Dist: beautifulsoup4
Requires-Dist: selenium
